{
  "lists": [
    {
      "id": 1,
      "title": "list 1"
    },
    {
      "id": 2,
      "title": "sometitle2"
    },
    {
      "title": "dfgdgf",
      "id": 3
    }
  ],
  "tasks": [
    {
      "id": 1,
      "title": "djnfksdf",
      "isComplete": true,
      "isUrgent": true,
      "listId": 1,
      "date": "2020-08-07T03:43:45.567Z"
    },
    {
      "id": 1,
      "title": "'task title2",
      "isComplete": false,
      "isUrgent": false,
      "listId": 2,
      "date": "2020-08-07T03:43:45.567Z"
    },
    {
      "id": 1,
      "title": "'task title2",
      "isComplete": false,
      "isUrgent": true,
      "listId": 2,
      "date": "2020-08-07T03:43:45.567Z"
    },
    {
      "title": "isUrgent",
      "isComplete": false,
      "isUrgent": true,
      "listId": "2",
      "id": 2,
      "date": "2020-08-07T03:43:45.567Z"
    },
    {
      "title": "isUrgent!",
      "isComplete": false,
      "isUrgent": false,
      "listId": "2",
      "id": 3,
      "date": "2020-08-07T03:43:45.567Z"
    },
    {
      "title": "fdfgdfg",
      "isComplete": false,
      "isUrgent": false,
      "listId": "2",
      "id": 4,
      "date": "2020-08-07T03:43:45.567Z"
    },
    {
      "title": "test",
      "isComplete": false,
      "isUrgent": false,
      "listId": "1",
      "id": 5,
      "date": "2020-08-07T03:43:45.567Z"
    },
    {
      "title": "sfsdf",
      "isComplete": false,
      "isUrgent": false,
      "listId": "2",
      "id": 6
    },
    {
      "title": "d7",
      "isComplete": false,
      "isUrgent": false,
      "date": "2020-08-07T03:47:18.424Z",
      "listId": "2",
      "id": 7
    },
    {
      "title": "e",
      "isComplete": false,
      "isUrgent": false,
      "date": "07.08.2020",
      "listId": "2",
      "id": 8
    },
    {
      "title": "5555",
      "isComplete": false,
      "isUrgent": false,
      "date": "07.08.2020, 10:49:42",
      "listId": "2",
      "id": 9
    },
    {
      "title": "33",
      "isComplete": false,
      "isUrgent": false,
      "date": "07.08.2020, 10:51:51",
      "listId": "2",
      "id": 10
    },
    {
      "title": "dfgdfg",
      "isComplete": false,
      "isUrgent": false,
      "date": "07.08.2020, 10:53:09",
      "listId": "2",
      "id": 11
    },
    {
      "title": "fdgdfg",
      "isComplete": false,
      "isUrgent": false,
      "date": "07.08.2020, 10:53:16",
      "listId": "2",
      "id": 12
    },
    {
      "title": "dgdf",
      "isComplete": false,
      "isUrgent": false,
      "date": "10:53",
      "listId": "2",
      "id": 13
    },
    {
      "title": "fdgdfg",
      "isComplete": false,
      "isUrgent": false,
      "date": "07.08.2020, 10:55",
      "listId": "2",
      "id": 14
    }
  ]
}